APICORE/__init__.py
APICORE/core.py
APICORE/parsers/__init__.py
APICORE/parsers/image.py
apicore_python-1.0.1.dist-info/licenses/LICENSE
apicore_python-1.0.1.dist-info/METADATA
apicore_python-1.0.1.dist-info/WHEEL
apicore_python-1.0.1.dist-info/top_level.txt
apicore_python-1.0.1.dist-info/RECORD
